pytest_aiofiles/plugin.py
pytest_aiofiles/urandom.py
pytest_aiofiles-0.2.0.dist-info/DESCRIPTION.rst
pytest_aiofiles-0.2.0.dist-info/METADATA
pytest_aiofiles-0.2.0.dist-info/RECORD
pytest_aiofiles-0.2.0.dist-info/WHEEL
pytest_aiofiles-0.2.0.dist-info/entry_points.txt
pytest_aiofiles-0.2.0.dist-info/metadata.json
pytest_aiofiles-0.2.0.dist-info/pbr.json
pytest_aiofiles-0.2.0.dist-info/top_level.txt
